love/__init__.py
love/__main__.py
love/flit.py
love/github.py
love/love.py
love/tests/test_love.py
love-0.0.3.dist-info/entry_points.txt
love-0.0.3.dist-info/WHEEL
love-0.0.3.dist-info/METADATA
love-0.0.3.dist-info/RECORD
