Metadata-Version: 1.2
Name: love
Version: 0.0.3
Summary: Package creation and management, using Love. 
Home-page: https://github.com/Carreau/love
License: UNKNOWN
Author: Matthias Bussonnier
Author-email: bussonniermatthias@gmail.com
Requires-Python: >=3.4
Classifier: License :: OSI Approved :: MIT License
Requires-Dist: emoji
Requires-Dist: pkgtools
Requires-Dist: pygithub
Requires-Dist: travispy
Requires-Dist: requests
Requires-Dist: keyring
Requires-Dist: colored
Requires-Dist: withlog
Requires-Dist: overprint
